setup.py
dHydra/__init__.py
dHydra/app.py
dHydra/auto.py
dHydra/cli.py
dHydra/console.py
dHydra/web.py
dHydra.egg-info/PKG-INFO
dHydra.egg-info/SOURCES.txt
dHydra.egg-info/dependency_links.txt
dHydra.egg-info/requires.txt
dHydra.egg-info/top_level.txt
dHydra.egg-info/zip-safe
dHydra/action/__init__.py
dHydra/action/Demo/DemoAction.py
dHydra/action/Demo/__init__.py
dHydra/action/Demo/config.py
dHydra/action/Demo/connection.py
dHydra/action/Demo/const.py
dHydra/action/PrintSinaL2/PrintSinaL2Action.py
dHydra/action/PrintSinaL2/__init__.py
dHydra/action/SinaL2TCP/SinaL2TCPAction.py
dHydra/action/SinaL2TCP/__init__.py
dHydra/action/SinaL2TCP/config.py
dHydra/action/SinaL2TCP/connection.py
dHydra/action/SinaL2TCP/const.py
dHydra/action/SinaTickToMongo/SinaTickToMongoAction.py
dHydra/action/SinaTickToMongo/__init__.py
dHydra/action/SinaTickToMongo/config.py
dHydra/action/SinaTickToMongo/connection.py
dHydra/action/SinaTickToMongo/const.py
dHydra/config/__init__.py
dHydra/config/config.py
dHydra/config/connection.py
dHydra/config/const.py
dHydra/core/Action.py
dHydra/core/Event.py
dHydra/core/Functions.py
dHydra/core/Globals.py
dHydra/core/Producer.py
dHydra/core/ThreadManager.py
dHydra/core/Vendor.py
dHydra/core/__init__.py
dHydra/core/util.py
dHydra/producer/__init__.py
dHydra/producer/SinaFreeQuote/SinaFreeQuoteProducer.py
dHydra/producer/SinaFreeQuote/__init__.py
dHydra/producer/SinaFreeQuote/config.py
dHydra/producer/SinaFreeQuote/connection.py
dHydra/producer/SinaFreeQuote/const.py
dHydra/producer/SinaLevel2WS/SinaLevel2WSProducer.py
dHydra/producer/SinaLevel2WS/__init__.py
dHydra/producer/SinaLevel2WS/config.py
dHydra/producer/SinaLevel2WS/connection.py
dHydra/producer/SinaLevel2WS/const.py
dHydra/vendor/__init__.py
dHydra/vendor/DB/DBVendor.py
dHydra/vendor/DB/__init__.py
dHydra/vendor/DB/config.py
dHydra/vendor/DB/connection.py
dHydra/vendor/DB/const.py
dHydra/vendor/Maoyan/MaoyanVendor.py
dHydra/vendor/Maoyan/__init__.py
dHydra/vendor/Maoyan/connection.py
dHydra/vendor/Sina/SinaVendor.py
dHydra/vendor/Sina/__init__.py
dHydra/vendor/Sina/config.py
dHydra/vendor/Sina/connection.py
dHydra/vendor/Sina/const.py
