Metadata-Version: 1.1
Name: dHydra
Version: 0.11.0
Summary: A framework for saving & data mining Chinese Stocks
Home-page: http://dHydra.org
Author: Wen Gu
Author-email: emptyset110@gmail.com
License: Apache Software License
Keywords: Finance,Chinese Stock,Quant,Framework
Platform: UNKNOWN
Classifier: License :: OSI Approved :: Apache Software License
Classifier: Programming Language :: Python
Classifier: Intended Audience :: Financial and Insurance Industry
Classifier: Operating System :: OS Independent
